Engine.py
Globals.py
MultiframeUtils.py
__init__.py
__pkginfo__.py
Constraints/AngleConstraints.py
Constraints/AtomicCoordinationConstraints.py
Constraints/BondConstraints.py
Constraints/Collection.py
Constraints/DihedralAngleConstraints.py
Constraints/DistanceConstraints.py
Constraints/ImproperAngleConstraints.py
Constraints/PairCorrelationConstraints.py
Constraints/PairDistributionConstraints.py
Constraints/StructureFactorConstraints.py
Constraints/__init__.py
Core/Collection.py
Core/Constraint.py
Core/Group.py
Core/GroupSelector.py
Core/MoveGenerator.py
Core/__init__.py
Examples/__init__.py
Generators/Agitations.py
Generators/Removes.py
Generators/Rotations.py
Generators/Swaps.py
Generators/Translations.py
Generators/__init__.py
Selectors/OrderedSelectors.py
Selectors/RandomSelectors.py
Selectors/__init__.py
fullrmc/Engine.py
fullrmc/Globals.py
fullrmc/MultiframeUtils.py
fullrmc/__init__.py
fullrmc/__pkginfo__.py
fullrmc/Constraints/AngleConstraints.py
fullrmc/Constraints/AtomicCoordinationConstraints.py
fullrmc/Constraints/BondConstraints.py
fullrmc/Constraints/Collection.py
fullrmc/Constraints/DihedralAngleConstraints.py
fullrmc/Constraints/DistanceConstraints.py
fullrmc/Constraints/ImproperAngleConstraints.py
fullrmc/Constraints/PairCorrelationConstraints.py
fullrmc/Constraints/PairDistributionConstraints.py
fullrmc/Constraints/StructureFactorConstraints.py
fullrmc/Constraints/__init__.py
fullrmc/Core/Collection.py
fullrmc/Core/Constraint.py
fullrmc/Core/Group.py
fullrmc/Core/GroupSelector.py
fullrmc/Core/MoveGenerator.py
fullrmc/Core/__init__.py
fullrmc/Core/angles.cpython-37m-darwin.so
fullrmc/Core/atomic_coordination.cpython-37m-darwin.so
fullrmc/Core/atomic_distances.cpython-37m-darwin.so
fullrmc/Core/bonds.cpython-37m-darwin.so
fullrmc/Core/boundary_conditions_collection.cpython-37m-darwin.so
fullrmc/Core/dihedral_angles.cpython-37m-darwin.so
fullrmc/Core/improper_angles.cpython-37m-darwin.so
fullrmc/Core/pairs_distances.cpython-37m-darwin.so
fullrmc-4.1.0.dist-info/METADATA
fullrmc-4.1.0.dist-info/WHEEL
fullrmc-4.1.0.dist-info/top_level.txt
fullrmc-4.1.0.dist-info/RECORD
