Metadata-Version: 2.1
Name: fullrmc
Version: 4.1.0
Summary: FUndamental Library Language for Reverse Monte Carlo or fullrmc is a molecular/atomic stochastic fitting platform to reverse modeling experimental data. 
Home-page: http://bachiraoun.github.io/fullrmc
Author: Bachir AOUN
Author-email: fullrmc@gmail.com
License: GNU
Download-URL: https://github.com/bachiraoun/fullrmc
Platform: Windows
Platform: Linux
Platform: Mac OS-X
Platform: Unix
Classifier: Development Status :: 4 - Beta
Classifier: Intended Audience :: Science/Research
Classifier: Intended Audience :: Education
Classifier: Intended Audience :: Developers
Classifier: Natural Language :: English
Classifier: License :: OSI Approved :: GNU Affero General Public License v3
Classifier: Programming Language :: Python :: 2.7
Classifier: Programming Language :: Python :: 3
Classifier: Programming Language :: Python :: 3.7
Classifier: Programming Language :: Cython
Classifier: Topic :: Software Development
Classifier: Topic :: Software Development :: Build Tools
Classifier: Topic :: Scientific/Engineering
Classifier: Topic :: Scientific/Engineering :: Artificial Intelligence
Classifier: Topic :: Scientific/Engineering :: Physics
Classifier: Topic :: Scientific/Engineering :: Mathematics
Classifier: Topic :: Scientific/Engineering :: Chemistry
Classifier: Operating System :: OS Independent
Classifier: Operating System :: Microsoft :: Windows
Classifier: Operating System :: POSIX
Classifier: Operating System :: Unix
Classifier: Operating System :: MacOS
Requires-Dist: pysimplelog (>=2.0.0)
Requires-Dist: pdbparser (>=0.1.8)
Requires-Dist: pyrep (>=3.2.0)
Requires-Dist: pylocker (>=3.0.0)
Requires-Dist: matplotlib (>=3.1.2)
